CHANGELOG.txt
LICENCE.txt
MANIFEST.in
README.txt
setup.py
Windows_Custom_File_Searcher.egg-info/PKG-INFO
Windows_Custom_File_Searcher.egg-info/SOURCES.txt
Windows_Custom_File_Searcher.egg-info/dependency_links.txt
Windows_Custom_File_Searcher.egg-info/top_level.txt
searcher_code/__init__.py
searcher_code/file_search.py
searcher_code/output.txt
searcher_code/output_limit.txt
searcher_code/trial1.py
searcher_code/trial2.py