Metadata-Version: 2.1
Name: Windows-Custom-File-Searcher
Version: 0.0.1
Summary: This is a simple command line custom file searcher for windows
Home-page: UNKNOWN
Author: Wycliffe Oloo
Author-email: wycliflocka@gmail.com
License: MIT
Keywords: search,searcher,file,windows,custom
Platform: UNKNOWN
Classifier: Development Status :: 1 - Planning
Classifier: Intended Audience :: Developers
Classifier: Operating System :: Microsoft :: Windows :: Windows 10
Classifier: License :: OSI Approved :: MIT License
Classifier: Programming Language :: Python :: 3
License-File: LICENCE.txt
